requests_har/__init__.py
requests_har/har.py
requests_har/py.typed
requests_har/session.py
requests_har/types.py
requests_har/version.py
requests_har-1.2.0.dist-info/LICENSE
requests_har-1.2.0.dist-info/METADATA
requests_har-1.2.0.dist-info/WHEEL
requests_har-1.2.0.dist-info/RECORD
