Metadata-Version: 2.1
Name: requests_har
Version: 1.2.0
Summary: HAR hook for the requests library
Home-page: https://github.com/sbordeyne/requests_har
License: MIT
Author: Dogeek
Author-email: simon.bordeyne@gmail.com
Requires-Python: >=3.9,<4.0
Classifier: License :: OSI Approved :: MIT License
Classifier: Programming Language :: Python :: 3
Classifier: Programming Language :: Python :: 3.9
Classifier: Programming Language :: Python :: 3.10
Classifier: Programming Language :: Python :: 3.11
Classifier: Programming Language :: Python :: 3.12
Classifier: Programming Language :: Python :: 3.8
Requires-Dist: requests (>=2.28.1,<3.0.0)
Project-URL: Repository, https://github.com/sbordeyne/requests_har
